[
    {
        "key": "datr",
        "value": "tUefZ2UxjwDiLaZ1F1yTL0be",
        "domain": "facebook.com",
        "path": "/",
        "hostOnly": false,
        "creation": "2025-02-06T14:09:35.084Z",
        "lastAccessed": "2025-02-06T14:09:35.085Z"
    },
    {
        "key": "sb",
        "value": "sEifZ07RV5gjohB9Sck7Hivv",
        "domain": "facebook.com",
        "path": "/",
        "hostOnly": false,
        "creation": "2025-02-06T14:09:35.085Z",
        "lastAccessed": "2025-02-06T14:09:35.085Z"
    },
    {
        "key": "vpd",
        "value": "v1%3B811x424x1.6815046072006226",
        "domain": "facebook.com",
        "path": "/",
        "hostOnly": false,
        "creation": "2025-02-06T14:09:35.085Z",
        "lastAccessed": "2025-02-06T14:09:35.085Z"
    },
    {
        "key": "dpr",
        "value": "1.5294095277786255",
        "domain": "facebook.com",
        "path": "/",
        "hostOnly": false,
        "creation": "2025-02-06T14:09:35.085Z",
        "lastAccessed": "2025-02-06T14:09:35.085Z"
    },
    {
        "key": "m_pixel_ratio",
        "value": "1.6815046072006226",
        "domain": "facebook.com",
        "path": "/",
        "hostOnly": false,
        "creation": "2025-02-06T14:09:35.085Z",
        "lastAccessed": "2025-02-06T14:09:35.085Z"
    },
    {
        "key": "wd",
        "value": "429x820",
        "domain": "facebook.com",
        "path": "/",
        "hostOnly": false,
        "creation": "2025-02-06T14:09:35.085Z",
        "lastAccessed": "2025-02-06T14:09:35.085Z"
    },
    {
        "key": "c_user",
        "value": "61550041252629",
        "domain": "facebook.com",
        "path": "/",
        "hostOnly": false,
        "creation": "2025-02-06T14:09:35.085Z",
        "lastAccessed": "2025-02-06T14:09:35.085Z"
    },
    {
        "key": "fr",
        "value": "0GVQ3NK8ueBsrdVhw.AWVRhjEZbgXuQtE50ClVrmWKM2dZ1atPommkEw.BnoCDy..AAA.0.0.BnpMF9.AWXYdJEQ_Nw",
        "domain": "facebook.com",
        "path": "/",
        "hostOnly": false,
        "creation": "2025-02-06T14:09:35.085Z",
        "lastAccessed": "2025-02-06T14:09:35.085Z"
    },
    {
        "key": "xs",
        "value": "8%3Az_M3EyTPjVSElg%3A2%3A1738850686%3A-1%3A5629",
        "domain": "facebook.com",
        "path": "/",
        "hostOnly": false,
        "creation": "2025-02-06T14:09:35.085Z",
        "lastAccessed": "2025-02-06T14:09:35.085Z"
    },
    {
        "key": "fbl_st",
        "value": "100439318%3BT%3A28980844",
        "domain": "facebook.com",
        "path": "/",
        "hostOnly": false,
        "creation": "2025-02-06T14:09:35.085Z",
        "lastAccessed": "2025-02-06T14:09:35.085Z"
    },
    {
        "key": "wl_cbv",
        "value": "v2%3Bclient_version%3A2733%3Btimestamp%3A1738850688",
        "domain": "facebook.com",
        "path": "/",
        "hostOnly": false,
        "creation": "2025-02-06T14:09:35.085Z",
        "lastAccessed": "2025-02-06T14:09:35.085Z"
    }
]
